{
    "total": 52,
    "subtotal": 52,
    "limit": null,
    "offset": null,
    "metadata": {
        "apiId": "t000009d2000000018-19885338af90dc7e71a4e574b82d0370-0",
        "title": "ダイオキシン類調査結果・H24大気 大気　ダイオキシン類異性体等分析結果（第4回調査：区部）",
        "datasetId": "t000009d2000000018",
        "datasetTitle": "ダイオキシン類調査結果・H24大気",
        "datasetDesc": "",
        "dataTitle": "大気　ダイオキシン類異性体等分析結果（第4回調査：区部）",
        "dataDesc": "",
        "sheetname": "",
        "version": "1.0.1",
        "created": "2021/03/29 10:25:00",
        "updated": "2021/03/29 10:25:00"
    },
    "hits": [
        {
            "row": 1,
            "column1": "実測濃度",
            "化合物の名称等": "ポリ塩化ジベンゾ|パラ|ジオキシン",
            "column2": "1,3,6,8-TeCDD",
            "毒性等価係数": "0",
            "定量下限（pg/m3）": "0.005",
            "検出下限（pg/m3）": "0.002",
            "(1)中央区晴海局／2月7日～2月14日（pg/m3）": "0.12",
            "(備考)": "",
            "(2)目黒区碑文谷局／2月7日～2月14日（pg/m3）": "0.07",
            "(備考)1": "",
            "(3)大田区東糀谷局／2月7日～2月14日（pg/m3）": "0.069",
            "(備考)2": "",
            "(4)世田谷区世田谷局／2月7日～2月14日（pg/m3）": "0.068",
            "(備考)3": "",
            "(5)中野区若宮局／2月7日～2月14日（pg/m3）": "0.07",
            "(備考)4": "",
            "(6)荒川区南千住局／2月7日～2月14日（pg/m3）": 0.19,
            "(備考)5": "",
            "(7)板橋区本町局／2月7日～2月14日（pg/m3）": "0.12",
            "(備考)6": "",
            "(8)練馬区石神井町局／2月7日～2月14日（pg/m3）": 0.2,
            "(備考)7": "",
            "(9)足立区西新井局／2月7日～2月14日（pg/m3）": "0.2",
            "(備考)8": "",
            "(10)葛飾区鎌倉／3月14日～3月21日（pg/m3）": "0.14",
            "(備考)9": "",
            "(11)江戸川区春江町局／2月7日～2月14日（pg/m3）": 0.12,
            "(備考)10": ""
        },
        {
            "row": 2,
            "column1": "実測濃度",
            "化合物の名称等": "ポリ塩化ジベンゾ|パラ|ジオキシン",
            "column2": "1,3,7,9-TeCDD",
            "毒性等価係数": "0",
            "定量下限（pg/m3）": "0.005",
            "検出下限（pg/m3）": "0.002",
            "(1)中央区晴海局／2月7日～2月14日（pg/m3）": "0.053",
            "(備考)": "",
            "(2)目黒区碑文谷局／2月7日～2月14日（pg/m3）": "0.03",
            "(備考)1": "",
            "(3)大田区東糀谷局／2月7日～2月14日（pg/m3）": "0.03",
            "(備考)2": "",
            "(4)世田谷区世田谷局／2月7日～2月14日（pg/m3）": "0.03",
            "(備考)3": "",
            "(5)中野区若宮局／2月7日～2月14日（pg/m3）": "0.028",
            "(備考)4": "",
            "(6)荒川区南千住局／2月7日～2月14日（pg/m3）": 0.099,
            "(備考)5": "",
            "(7)板橋区本町局／2月7日～2月14日（pg/m3）": "0.056",
            "(備考)6": "",
            "(8)練馬区石神井町局／2月7日～2月14日（pg/m3）": 0.086,
            "(備考)7": "",
            "(9)足立区西新井局／2月7日～2月14日（pg/m3）": "0.11",
            "(備考)8": "",
            "(10)葛飾区鎌倉／3月14日～3月21日（pg/m3）": "0.056",
            "(備考)9": "",
            "(11)江戸川区春江町局／2月7日～2月14日（pg/m3）": 0.056,
            "(備考)10": ""
        },
        {
            "row": 3,
            "column1": "実測濃度",
            "化合物の名称等": "ポリ塩化ジベンゾ|パラ|ジオキシン",
            "column2": "2,3,7,8-TeCDD",
            "毒性等価係数": "1",
            "定量下限（pg/m3）": "0.005",
            "検出下限（pg/m3）": "0.002",
            "(1)中央区晴海局／2月7日～2月14日（pg/m3）": "N.D.",
            "(備考)": "",
            "(2)目黒区碑文谷局／2月7日～2月14日（pg/m3）": "N.D.",
            "(備考)1": "",
            "(3)大田区東糀谷局／2月7日～2月14日（pg/m3）": "N.D.",
            "(備考)2": "",
            "(4)世田谷区世田谷局／2月7日～2月14日（pg/m3）": "N.D.",
            "(備考)3": "",
            "(5)中野区若宮局／2月7日～2月14日（pg/m3）": "N.D.",
            "(備考)4": "",
            "(6)荒川区南千住局／2月7日～2月14日（pg/m3）": 0.003,
            "(備考)5": "*",
            "(7)板橋区本町局／2月7日～2月14日（pg/m3）": "N.D.",
            "(備考)6": "",
            "(8)練馬区石神井町局／2月7日～2月14日（pg/m3）": 0.003,
            "(備考)7": "*",
            "(9)足立区西新井局／2月7日～2月14日（pg/m3）": "N.D.",
            "(備考)8": "",
            "(10)葛飾区鎌倉／3月14日～3月21日（pg/m3）": "N.D.",
            "(備考)9": "",
            "(11)江戸川区春江町局／2月7日～2月14日（pg/m3）": 0.002,
            "(備考)10": "*"
        },
        {
            "row": 4,
            "column1": "実測濃度",
            "化合物の名称等": "ポリ塩化ジベンゾ|パラ|ジオキシン",
            "column2": "TeCDDs",
            "毒性等価係数": "－",
            "定量下限（pg/m3）": "0.005",
            "検出下限（pg/m3）": "0.002",
            "(1)中央区晴海局／2月7日～2月14日（pg/m3）": "0.23",
            "(備考)": "",
            "(2)目黒区碑文谷局／2月7日～2月14日（pg/m3）": "0.13",
            "(備考)1": "",
            "(3)大田区東糀谷局／2月7日～2月14日（pg/m3）": "0.14",
            "(備考)2": "",
            "(4)世田谷区世田谷局／2月7日～2月14日（pg/m3）": "0.14",
            "(備考)3": "",
            "(5)中野区若宮局／2月7日～2月14日（pg/m3）": "0.14",
            "(備考)4": "",
            "(6)荒川区南千住局／2月7日～2月14日（pg/m3）": 0.4,
            "(備考)5": "",
            "(7)板橋区本町局／2月7日～2月14日（pg/m3）": "0.24",
            "(備考)6": "",
            "(8)練馬区石神井町局／2月7日～2月14日（pg/m3）": 0.42,
            "(備考)7": "",
            "(9)足立区西新井局／2月7日～2月14日（pg/m3）": "0.41",
            "(備考)8": "",
            "(10)葛飾区鎌倉／3月14日～3月21日（pg/m3）": "0.25",
            "(備考)9": "",
            "(11)江戸川区春江町局／2月7日～2月14日（pg/m3）": 0.27,
            "(備考)10": ""
        },
        {
            "row": 5,
            "column1": "実測濃度",
            "化合物の名称等": "ポリ塩化ジベンゾ|パラ|ジオキシン",
            "column2": "1,2,3,7,8-PeCDD",
            "毒性等価係数": "1",
            "定量下限（pg/m3）": "0.006",
            "検出下限（pg/m3）": "0.002",
            "(1)中央区晴海局／2月7日～2月14日（pg/m3）": "0.007",
            "(備考)": "",
            "(2)目黒区碑文谷局／2月7日～2月14日（pg/m3）": "0.004",
            "(備考)1": "*",
            "(3)大田区東糀谷局／2月7日～2月14日（pg/m3）": "0.005",
            "(備考)2": "*",
            "(4)世田谷区世田谷局／2月7日～2月14日（pg/m3）": "0.006",
            "(備考)3": "",
            "(5)中野区若宮局／2月7日～2月14日（pg/m3）": "0.006",
            "(備考)4": "",
            "(6)荒川区南千住局／2月7日～2月14日（pg/m3）": 0.01,
            "(備考)5": "",
            "(7)板橋区本町局／2月7日～2月14日（pg/m3）": "0.007",
            "(備考)6": "",
            "(8)練馬区石神井町局／2月7日～2月14日（pg/m3）": 0.012,
            "(備考)7": "",
            "(9)足立区西新井局／2月7日～2月14日（pg/m3）": "0.009",
            "(備考)8": "",
            "(10)葛飾区鎌倉／3月14日～3月21日（pg/m3）": "0.004",
            "(備考)9": "*",
            "(11)江戸川区春江町局／2月7日～2月14日（pg/m3）": 0.013,
            "(備考)10": ""
        },
        {
            "row": 6,
            "column1": "実測濃度",
            "化合物の名称等": "ポリ塩化ジベンゾ|パラ|ジオキシン",
            "column2": "PeCDDs",
            "毒性等価係数": "－",
            "定量下限（pg/m3）": "0.006",
            "検出下限（pg/m3）": "0.002",
            "(1)中央区晴海局／2月7日～2月14日（pg/m3）": "0.16",
            "(備考)": "",
            "(2)目黒区碑文谷局／2月7日～2月14日（pg/m3）": "0.09",
            "(備考)1": "",
            "(3)大田区東糀谷局／2月7日～2月14日（pg/m3）": "0.096",
            "(備考)2": "",
            "(4)世田谷区世田谷局／2月7日～2月14日（pg/m3）": "0.12",
            "(備考)3": "",
            "(5)中野区若宮局／2月7日～2月14日（pg/m3）": "0.12",
            "(備考)4": "",
            "(6)荒川区南千住局／2月7日～2月14日（pg/m3）": 0.29,
            "(備考)5": "",
            "(7)板橋区本町局／2月7日～2月14日（pg/m3）": "0.16",
            "(備考)6": "",
            "(8)練馬区石神井町局／2月7日～2月14日（pg/m3）": 0.25,
            "(備考)7": "",
            "(9)足立区西新井局／2月7日～2月14日（pg/m3）": "0.35",
            "(備考)8": "",
            "(10)葛飾区鎌倉／3月14日～3月21日（pg/m3）": "0.11",
            "(備考)9": "",
            "(11)江戸川区春江町局／2月7日～2月14日（pg/m3）": 0.22,
            "(備考)10": ""
        },
        {
            "row": 7,
            "column1": "実測濃度",
            "化合物の名称等": "ポリ塩化ジベンゾ|パラ|ジオキシン",
            "column2": "1,2,3,4,7,8-HxCDD",
            "毒性等価係数": "0.1",
            "定量下限（pg/m3）": "0.010",
            "検出下限（pg/m3）": "0.003",
            "(1)中央区晴海局／2月7日～2月14日（pg/m3）": "0.005",
            "(備考)": "*",
            "(2)目黒区碑文谷局／2月7日～2月14日（pg/m3）": "0.005",
            "(備考)1": "*",
            "(3)大田区東糀谷局／2月7日～2月14日（pg/m3）": "0.004",
            "(備考)2": "*",
            "(4)世田谷区世田谷局／2月7日～2月14日（pg/m3）": "0.006",
            "(備考)3": "*",
            "(5)中野区若宮局／2月7日～2月14日（pg/m3）": "0.006",
            "(備考)4": "*",
            "(6)荒川区南千住局／2月7日～2月14日（pg/m3）": 0.009,
            "(備考)5": "*",
            "(7)板橋区本町局／2月7日～2月14日（pg/m3）": "0.007",
            "(備考)6": "*",
            "(8)練馬区石神井町局／2月7日～2月14日（pg/m3）": 0.011,
            "(備考)7": "",
            "(9)足立区西新井局／2月7日～2月14日（pg/m3）": "0.009",
            "(備考)8": "*",
            "(10)葛飾区鎌倉／3月14日～3月21日（pg/m3）": "0.004",
            "(備考)9": "*",
            "(11)江戸川区春江町局／2月7日～2月14日（pg/m3）": 0.011,
            "(備考)10": ""
        },
        {
            "row": 8,
            "column1": "実測濃度",
            "化合物の名称等": "ポリ塩化ジベンゾ|パラ|ジオキシン",
            "column2": "1,2,3,6,7,8-HxCDD",
            "毒性等価係数": "0.1",
            "定量下限（pg/m3）": "0.009",
            "検出下限（pg/m3）": "0.002",
            "(1)中央区晴海局／2月7日～2月14日（pg/m3）": "0.011",
            "(備考)": "",
            "(2)目黒区碑文谷局／2月7日～2月14日（pg/m3）": "0.007",
            "(備考)1": "*",
            "(3)大田区東糀谷局／2月7日～2月14日（pg/m3）": "0.007",
            "(備考)2": "*",
            "(4)世田谷区世田谷局／2月7日～2月14日（pg/m3）": "0.011",
            "(備考)3": "",
            "(5)中野区若宮局／2月7日～2月14日（pg/m3）": "0.01",
            "(備考)4": "",
            "(6)荒川区南千住局／2月7日～2月14日（pg/m3）": 0.016,
            "(備考)5": "",
            "(7)板橋区本町局／2月7日～2月14日（pg/m3）": "0.012",
            "(備考)6": "",
            "(8)練馬区石神井町局／2月7日～2月14日（pg/m3）": 0.02,
            "(備考)7": "",
            "(9)足立区西新井局／2月7日～2月14日（pg/m3）": "0.018",
            "(備考)8": "",
            "(10)葛飾区鎌倉／3月14日～3月21日（pg/m3）": "0.009",
            "(備考)9": "",
            "(11)江戸川区春江町局／2月7日～2月14日（pg/m3）": 0.015,
            "(備考)10": ""
        },
        {
            "row": 9,
            "column1": "実測濃度",
            "化合物の名称等": "ポリ塩化ジベンゾ|パラ|ジオキシン",
            "column2": "1,2,3,7,8,9-HxCDD",
            "毒性等価係数": "0.1",
            "定量下限（pg/m3）": "0.009",
            "検出下限（pg/m3）": "0.003",
            "(1)中央区晴海局／2月7日～2月14日（pg/m3）": "0.009",
            "(備考)": "",
            "(2)目黒区碑文谷局／2月7日～2月14日（pg/m3）": "0.006",
            "(備考)1": "*",
            "(3)大田区東糀谷局／2月7日～2月14日（pg/m3）": "0.007",
            "(備考)2": "*",
            "(4)世田谷区世田谷局／2月7日～2月14日（pg/m3）": "0.007",
            "(備考)3": "*",
            "(5)中野区若宮局／2月7日～2月14日（pg/m3）": "0.007",
            "(備考)4": "*",
            "(6)荒川区南千住局／2月7日～2月14日（pg/m3）": 0.013,
            "(備考)5": "",
            "(7)板橋区本町局／2月7日～2月14日（pg/m3）": "0.01",
            "(備考)6": "",
            "(8)練馬区石神井町局／2月7日～2月14日（pg/m3）": 0.016,
            "(備考)7": "",
            "(9)足立区西新井局／2月7日～2月14日（pg/m3）": "0.012",
            "(備考)8": "",
            "(10)葛飾区鎌倉／3月14日～3月21日（pg/m3）": "0.007",
            "(備考)9": "*",
            "(11)江戸川区春江町局／2月7日～2月14日（pg/m3）": 0.017,
            "(備考)10": ""
        },
        {
            "row": 10,
            "column1": "実測濃度",
            "化合物の名称等": "ポリ塩化ジベンゾ|パラ|ジオキシン",
            "column2": "HxCDDs",
            "毒性等価係数": "－",
            "定量下限（pg/m3）": "0.009",
            "検出下限（pg/m3）": "0.002",
            "(1)中央区晴海局／2月7日～2月14日（pg/m3）": "0.15",
            "(備考)": "",
            "(2)目黒区碑文谷局／2月7日～2月14日（pg/m3）": "0.1",
            "(備考)1": "",
            "(3)大田区東糀谷局／2月7日～2月14日（pg/m3）": "0.11",
            "(備考)2": "",
            "(4)世田谷区世田谷局／2月7日～2月14日（pg/m3）": "0.15",
            "(備考)3": "",
            "(5)中野区若宮局／2月7日～2月14日（pg/m3）": "0.15",
            "(備考)4": "",
            "(6)荒川区南千住局／2月7日～2月14日（pg/m3）": 0.25,
            "(備考)5": "",
            "(7)板橋区本町局／2月7日～2月14日（pg/m3）": "0.18",
            "(備考)6": "",
            "(8)練馬区石神井町局／2月7日～2月14日（pg/m3）": 0.3,
            "(備考)7": "",
            "(9)足立区西新井局／2月7日～2月14日（pg/m3）": "0.3",
            "(備考)8": "",
            "(10)葛飾区鎌倉／3月14日～3月21日（pg/m3）": "0.12",
            "(備考)9": "",
            "(11)江戸川区春江町局／2月7日～2月14日（pg/m3）": 0.23,
            "(備考)10": ""
        },
        {
            "row": 11,
            "column1": "実測濃度",
            "化合物の名称等": "ポリ塩化ジベンゾ|パラ|ジオキシン",
            "column2": "1,2,3,4,6,7,8-HpCDD",
            "毒性等価係数": "0.01",
            "定量下限（pg/m3）": "0.010",
            "検出下限（pg/m3）": "0.003",
            "(1)中央区晴海局／2月7日～2月14日（pg/m3）": "0.066",
            "(備考)": "",
            "(2)目黒区碑文谷局／2月7日～2月14日（pg/m3）": "0.046",
            "(備考)1": "",
            "(3)大田区東糀谷局／2月7日～2月14日（pg/m3）": "0.049",
            "(備考)2": "",
            "(4)世田谷区世田谷局／2月7日～2月14日（pg/m3）": "0.062",
            "(備考)3": "",
            "(5)中野区若宮局／2月7日～2月14日（pg/m3）": "0.07",
            "(備考)4": "",
            "(6)荒川区南千住局／2月7日～2月14日（pg/m3）": 0.087,
            "(備考)5": "",
            "(7)板橋区本町局／2月7日～2月14日（pg/m3）": "0.083",
            "(備考)6": "",
            "(8)練馬区石神井町局／2月7日～2月14日（pg/m3）": 0.16,
            "(備考)7": "",
            "(9)足立区西新井局／2月7日～2月14日（pg/m3）": "0.089",
            "(備考)8": "",
            "(10)葛飾区鎌倉／3月14日～3月21日（pg/m3）": "0.051",
            "(備考)9": "",
            "(11)江戸川区春江町局／2月7日～2月14日（pg/m3）": 0.1,
            "(備考)10": ""
        },
        {
            "row": 12,
            "column1": "実測濃度",
            "化合物の名称等": "ポリ塩化ジベンゾ|パラ|ジオキシン",
            "column2": "HpCDDs",
            "毒性等価係数": "－",
            "定量下限（pg/m3）": "0.010",
            "検出下限（pg/m3）": "0.003",
            "(1)中央区晴海局／2月7日～2月14日（pg/m3）": "0.14",
            "(備考)": "",
            "(2)目黒区碑文谷局／2月7日～2月14日（pg/m3）": "0.095",
            "(備考)1": "",
            "(3)大田区東糀谷局／2月7日～2月14日（pg/m3）": "0.099",
            "(備考)2": "",
            "(4)世田谷区世田谷局／2月7日～2月14日（pg/m3）": "0.13",
            "(備考)3": "",
            "(5)中野区若宮局／2月7日～2月14日（pg/m3）": "0.14",
            "(備考)4": "",
            "(6)荒川区南千住局／2月7日～2月14日（pg/m3）": 0.18,
            "(備考)5": "",
            "(7)板橋区本町局／2月7日～2月14日（pg/m3）": "0.17",
            "(備考)6": "",
            "(8)練馬区石神井町局／2月7日～2月14日（pg/m3）": 0.32,
            "(備考)7": "",
            "(9)足立区西新井局／2月7日～2月14日（pg/m3）": "0.19",
            "(備考)8": "",
            "(10)葛飾区鎌倉／3月14日～3月21日（pg/m3）": "0.1",
            "(備考)9": "",
            "(11)江戸川区春江町局／2月7日～2月14日（pg/m3）": 0.21,
            "(備考)10": ""
        },
        {
            "row": 13,
            "column1": "実測濃度",
            "化合物の名称等": "ポリ塩化ジベンゾ|パラ|ジオキシン",
            "column2": "OCDD",
            "毒性等価係数": "0.0003",
            "定量下限（pg/m3）": "0.024",
            "検出下限（pg/m3）": "0.008",
            "(1)中央区晴海局／2月7日～2月14日（pg/m3）": "0.26",
            "(備考)": "",
            "(2)目黒区碑文谷局／2月7日～2月14日（pg/m3）": "0.2",
            "(備考)1": "",
            "(3)大田区東糀谷局／2月7日～2月14日（pg/m3）": "0.21",
            "(備考)2": "",
            "(4)世田谷区世田谷局／2月7日～2月14日（pg/m3）": "0.25",
            "(備考)3": "",
            "(5)中野区若宮局／2月7日～2月14日（pg/m3）": "0.25",
            "(備考)4": "",
            "(6)荒川区南千住局／2月7日～2月14日（pg/m3）": 0.31,
            "(備考)5": "",
            "(7)板橋区本町局／2月7日～2月14日（pg/m3）": "0.34",
            "(備考)6": "",
            "(8)練馬区石神井町局／2月7日～2月14日（pg/m3）": 0.64,
            "(備考)7": "",
            "(9)足立区西新井局／2月7日～2月14日（pg/m3）": "0.3",
            "(備考)8": "",
            "(10)葛飾区鎌倉／3月14日～3月21日（pg/m3）": "0.18",
            "(備考)9": "",
            "(11)江戸川区春江町局／2月7日～2月14日（pg/m3）": 0.34,
            "(備考)10": ""
        },
        {
            "row": 14,
            "column1": "実測濃度",
            "化合物の名称等": "ポリ塩化ジベンゾ|パラ|ジオキシン",
            "column2": "Total　PCDDs",
            "毒性等価係数": "－",
            "定量下限（pg/m3）": "－",
            "検出下限（pg/m3）": "－",
            "(1)中央区晴海局／2月7日～2月14日（pg/m3）": "0.94",
            "(備考)": "",
            "(2)目黒区碑文谷局／2月7日～2月14日（pg/m3）": "0.62",
            "(備考)1": "",
            "(3)大田区東糀谷局／2月7日～2月14日（pg/m3）": "0.66",
            "(備考)2": "",
            "(4)世田谷区世田谷局／2月7日～2月14日（pg/m3）": "0.79",
            "(備考)3": "",
            "(5)中野区若宮局／2月7日～2月14日（pg/m3）": "0.8",
            "(備考)4": "",
            "(6)荒川区南千住局／2月7日～2月14日（pg/m3）": 1.4,
            "(備考)5": "",
            "(7)板橋区本町局／2月7日～2月14日（pg/m3）": "1.1",
            "(備考)6": "",
            "(8)練馬区石神井町局／2月7日～2月14日（pg/m3）": 1.9,
            "(備考)7": "",
            "(9)足立区西新井局／2月7日～2月14日（pg/m3）": "1.6",
            "(備考)8": "",
            "(10)葛飾区鎌倉／3月14日～3月21日（pg/m3）": "0.76",
            "(備考)9": "",
            "(11)江戸川区春江町局／2月7日～2月14日（pg/m3）": 1.3,
            "(備考)10": ""
        },
        {
            "row": 15,
            "column1": "実測濃度",
            "化合物の名称等": "ポリ塩化ジベンゾフラン",
            "column2": "1,3,6,8-TeCDF",
            "毒性等価係数": "0",
            "定量下限（pg/m3）": "0.005",
            "検出下限（pg/m3）": "0.002",
            "(1)中央区晴海局／2月7日～2月14日（pg/m3）": "0.026",
            "(備考)": "",
            "(2)目黒区碑文谷局／2月7日～2月14日（pg/m3）": "0.013",
            "(備考)1": "",
            "(3)大田区東糀谷局／2月7日～2月14日（pg/m3）": "0.017",
            "(備考)2": "",
            "(4)世田谷区世田谷局／2月7日～2月14日（pg/m3）": "0.02",
            "(備考)3": "",
            "(5)中野区若宮局／2月7日～2月14日（pg/m3）": "0.017",
            "(備考)4": "",
            "(6)荒川区南千住局／2月7日～2月14日（pg/m3）": 0.039,
            "(備考)5": "",
            "(7)板橋区本町局／2月7日～2月14日（pg/m3）": "0.027",
            "(備考)6": "",
            "(8)練馬区石神井町局／2月7日～2月14日（pg/m3）": 0.048,
            "(備考)7": "",
            "(9)足立区西新井局／2月7日～2月14日（pg/m3）": "0.033",
            "(備考)8": "",
            "(10)葛飾区鎌倉／3月14日～3月21日（pg/m3）": "0.028",
            "(備考)9": "",
            "(11)江戸川区春江町局／2月7日～2月14日（pg/m3）": 0.039,
            "(備考)10": ""
        },
        {
            "row": 16,
            "column1": "実測濃度",
            "化合物の名称等": "ポリ塩化ジベンゾフラン",
            "column2": "1,2,7,8-TeCDF",
            "毒性等価係数": "0",
            "定量下限（pg/m3）": "0.005",
            "検出下限（pg/m3）": "0.002",
            "(1)中央区晴海局／2月7日～2月14日（pg/m3）": "0.023",
            "(備考)": "",
            "(2)目黒区碑文谷局／2月7日～2月14日（pg/m3）": "0.015",
            "(備考)1": "",
            "(3)大田区東糀谷局／2月7日～2月14日（pg/m3）": "0.02",
            "(備考)2": "",
            "(4)世田谷区世田谷局／2月7日～2月14日（pg/m3）": "0.018",
            "(備考)3": "",
            "(5)中野区若宮局／2月7日～2月14日（pg/m3）": "0.018",
            "(備考)4": "",
            "(6)荒川区南千住局／2月7日～2月14日（pg/m3）": 0.034,
            "(備考)5": "",
            "(7)板橋区本町局／2月7日～2月14日（pg/m3）": "0.025",
            "(備考)6": "",
            "(8)練馬区石神井町局／2月7日～2月14日（pg/m3）": 0.053,
            "(備考)7": "",
            "(9)足立区西新井局／2月7日～2月14日（pg/m3）": "0.028",
            "(備考)8": "",
            "(10)葛飾区鎌倉／3月14日～3月21日（pg/m3）": "0.026",
            "(備考)9": "",
            "(11)江戸川区春江町局／2月7日～2月14日（pg/m3）": 0.034,
            "(備考)10": ""
        },
        {
            "row": 17,
            "column1": "実測濃度",
            "化合物の名称等": "ポリ塩化ジベンゾフラン",
            "column2": "2,3,7,8-TeCDF",
            "毒性等価係数": "0.1",
            "定量下限（pg/m3）": "0.005",
            "検出下限（pg/m3）": "0.002",
            "(1)中央区晴海局／2月7日～2月14日（pg/m3）": "0.016",
            "(備考)": "",
            "(2)目黒区碑文谷局／2月7日～2月14日（pg/m3）": "0.008",
            "(備考)1": "",
            "(3)大田区東糀谷局／2月7日～2月14日（pg/m3）": "0.013",
            "(備考)2": "",
            "(4)世田谷区世田谷局／2月7日～2月14日（pg/m3）": "0.012",
            "(備考)3": "",
            "(5)中野区若宮局／2月7日～2月14日（pg/m3）": "0.01",
            "(備考)4": "",
            "(6)荒川区南千住局／2月7日～2月14日（pg/m3）": 0.022,
            "(備考)5": "",
            "(7)板橋区本町局／2月7日～2月14日（pg/m3）": "0.016",
            "(備考)6": "",
            "(8)練馬区石神井町局／2月7日～2月14日（pg/m3）": 0.029,
            "(備考)7": "",
            "(9)足立区西新井局／2月7日～2月14日（pg/m3）": "0.018",
            "(備考)8": "",
            "(10)葛飾区鎌倉／3月14日～3月21日（pg/m3）": "0.014",
            "(備考)9": "",
            "(11)江戸川区春江町局／2月7日～2月14日（pg/m3）": 0.021,
            "(備考)10": ""
        },
        {
            "row": 18,
            "column1": "実測濃度",
            "化合物の名称等": "ポリ塩化ジベンゾフラン",
            "column2": "TeCDFs",
            "毒性等価係数": "－",
            "定量下限（pg/m3）": "0.005",
            "検出下限（pg/m3）": "0.002",
            "(1)中央区晴海局／2月7日～2月14日（pg/m3）": "0.55",
            "(備考)": "",
            "(2)目黒区碑文谷局／2月7日～2月14日（pg/m3）": "0.35",
            "(備考)1": "",
            "(3)大田区東糀谷局／2月7日～2月14日（pg/m3）": "0.44",
            "(備考)2": "",
            "(4)世田谷区世田谷局／2月7日～2月14日（pg/m3）": "0.43",
            "(備考)3": "",
            "(5)中野区若宮局／2月7日～2月14日（pg/m3）": "0.41",
            "(備考)4": "",
            "(6)荒川区南千住局／2月7日～2月14日（pg/m3）": 0.92,
            "(備考)5": "",
            "(7)板橋区本町局／2月7日～2月14日（pg/m3）": "0.64",
            "(備考)6": "",
            "(8)練馬区石神井町局／2月7日～2月14日（pg/m3）": 1.3,
            "(備考)7": "",
            "(9)足立区西新井局／2月7日～2月14日（pg/m3）": "0.88",
            "(備考)8": "",
            "(10)葛飾区鎌倉／3月14日～3月21日（pg/m3）": "0.62",
            "(備考)9": "",
            "(11)江戸川区春江町局／2月7日～2月14日（pg/m3）": 0.81,
            "(備考)10": ""
        },
        {
            "row": 19,
            "column1": "実測濃度",
            "化合物の名称等": "ポリ塩化ジベンゾフラン",
            "column2": "1,2,3,7,8-PeCDF",
            "毒性等価係数": "0.03",
            "定量下限（pg/m3）": "0.005",
            "検出下限（pg/m3）": "0.002",
            "(1)中央区晴海局／2月7日～2月14日（pg/m3）": "0.018",
            "(備考)": "",
            "(2)目黒区碑文谷局／2月7日～2月14日（pg/m3）": "0.012",
            "(備考)1": "",
            "(3)大田区東糀谷局／2月7日～2月14日（pg/m3）": "0.011",
            "(備考)2": "",
            "(4)世田谷区世田谷局／2月7日～2月14日（pg/m3）": "0.016",
            "(備考)3": "",
            "(5)中野区若宮局／2月7日～2月14日（pg/m3）": "0.015",
            "(備考)4": "",
            "(6)荒川区南千住局／2月7日～2月14日（pg/m3）": 0.025,
            "(備考)5": "",
            "(7)板橋区本町局／2月7日～2月14日（pg/m3）": "0.02",
            "(備考)6": "",
            "(8)練馬区石神井町局／2月7日～2月14日（pg/m3）": 0.03,
            "(備考)7": "",
            "(9)足立区西新井局／2月7日～2月14日（pg/m3）": "0.026",
            "(備考)8": "",
            "(10)葛飾区鎌倉／3月14日～3月21日（pg/m3）": "0.014",
            "(備考)9": "",
            "(11)江戸川区春江町局／2月7日～2月14日（pg/m3）": 0.027,
            "(備考)10": ""
        },
        {
            "row": 20,
            "column1": "実測濃度",
            "化合物の名称等": "ポリ塩化ジベンゾフラン",
            "column2": "2,3,4,7,8-PeCDF",
            "毒性等価係数": "0.3",
            "定量下限（pg/m3）": "0.005",
            "検出下限（pg/m3）": "0.002",
            "(1)中央区晴海局／2月7日～2月14日（pg/m3）": "0.028",
            "(備考)": "",
            "(2)目黒区碑文谷局／2月7日～2月14日（pg/m3）": "0.016",
            "(備考)1": "",
            "(3)大田区東糀谷局／2月7日～2月14日（pg/m3）": "0.016",
            "(備考)2": "",
            "(4)世田谷区世田谷局／2月7日～2月14日（pg/m3）": "0.021",
            "(備考)3": "",
            "(5)中野区若宮局／2月7日～2月14日（pg/m3）": "0.024",
            "(備考)4": "",
            "(6)荒川区南千住局／2月7日～2月14日（pg/m3）": 0.035,
            "(備考)5": "",
            "(7)板橋区本町局／2月7日～2月14日（pg/m3）": "0.029",
            "(備考)6": "",
            "(8)練馬区石神井町局／2月7日～2月14日（pg/m3）": 0.044,
            "(備考)7": "",
            "(9)足立区西新井局／2月7日～2月14日（pg/m3）": "0.039",
            "(備考)8": "",
            "(10)葛飾区鎌倉／3月14日～3月21日（pg/m3）": "0.016",
            "(備考)9": "",
            "(11)江戸川区春江町局／2月7日～2月14日（pg/m3）": 0.035,
            "(備考)10": ""
        },
        {
            "row": 21,
            "column1": "実測濃度",
            "化合物の名称等": "ポリ塩化ジベンゾフラン",
            "column2": "PeCDFs",
            "毒性等価係数": "－",
            "定量下限（pg/m3）": "0.005",
            "検出下限（pg/m3）": "0.002",
            "(1)中央区晴海局／2月7日～2月14日（pg/m3）": "0.41",
            "(備考)": "",
            "(2)目黒区碑文谷局／2月7日～2月14日（pg/m3）": "0.25",
            "(備考)1": "",
            "(3)大田区東糀谷局／2月7日～2月14日（pg/m3）": "0.28",
            "(備考)2": "",
            "(4)世田谷区世田谷局／2月7日～2月14日（pg/m3）": "0.34",
            "(備考)3": "",
            "(5)中野区若宮局／2月7日～2月14日（pg/m3）": "0.35",
            "(備考)4": "",
            "(6)荒川区南千住局／2月7日～2月14日（pg/m3）": 0.6,
            "(備考)5": "",
            "(7)板橋区本町局／2月7日～2月14日（pg/m3）": "0.45",
            "(備考)6": "",
            "(8)練馬区石神井町局／2月7日～2月14日（pg/m3）": 0.72,
            "(備考)7": "",
            "(9)足立区西新井局／2月7日～2月14日（pg/m3）": "0.66",
            "(備考)8": "",
            "(10)葛飾区鎌倉／3月14日～3月21日（pg/m3）": "0.37",
            "(備考)9": "",
            "(11)江戸川区春江町局／2月7日～2月14日（pg/m3）": 0.56,
            "(備考)10": ""
        },
        {
            "row": 22,
            "column1": "実測濃度",
            "化合物の名称等": "ポリ塩化ジベンゾフラン",
            "column2": "1,2,3,4,7,8-HxCDF",
            "毒性等価係数": "0.1",
            "定量下限（pg/m3）": "0.010",
            "検出下限（pg/m3）": "0.003",
            "(1)中央区晴海局／2月7日～2月14日（pg/m3）": "0.034",
            "(備考)": "",
            "(2)目黒区碑文谷局／2月7日～2月14日（pg/m3）": "0.019",
            "(備考)1": "",
            "(3)大田区東糀谷局／2月7日～2月14日（pg/m3）": "0.022",
            "(備考)2": "",
            "(4)世田谷区世田谷局／2月7日～2月14日（pg/m3）": "0.029",
            "(備考)3": "",
            "(5)中野区若宮局／2月7日～2月14日（pg/m3）": "0.032",
            "(備考)4": "",
            "(6)荒川区南千住局／2月7日～2月14日（pg/m3）": 0.044,
            "(備考)5": "",
            "(7)板橋区本町局／2月7日～2月14日（pg/m3）": "0.037",
            "(備考)6": "",
            "(8)練馬区石神井町局／2月7日～2月14日（pg/m3）": 0.06,
            "(備考)7": "",
            "(9)足立区西新井局／2月7日～2月14日（pg/m3）": "0.051",
            "(備考)8": "",
            "(10)葛飾区鎌倉／3月14日～3月21日（pg/m3）": "0.024",
            "(備考)9": "",
            "(11)江戸川区春江町局／2月7日～2月14日（pg/m3）": 0.045,
            "(備考)10": ""
        },
        {
            "row": 23,
            "column1": "実測濃度",
            "化合物の名称等": "ポリ塩化ジベンゾフラン",
            "column2": "1,2,3,6,7,8-HxCDF",
            "毒性等価係数": "0.1",
            "定量下限（pg/m3）": "0.010",
            "検出下限（pg/m3）": "0.003",
            "(1)中央区晴海局／2月7日～2月14日（pg/m3）": "0.033",
            "(備考)": "",
            "(2)目黒区碑文谷局／2月7日～2月14日（pg/m3）": "0.02",
            "(備考)1": "",
            "(3)大田区東糀谷局／2月7日～2月14日（pg/m3）": "0.021",
            "(備考)2": "",
            "(4)世田谷区世田谷局／2月7日～2月14日（pg/m3）": "0.028",
            "(備考)3": "",
            "(5)中野区若宮局／2月7日～2月14日（pg/m3）": "0.033",
            "(備考)4": "",
            "(6)荒川区南千住局／2月7日～2月14日（pg/m3）": 0.041,
            "(備考)5": "",
            "(7)板橋区本町局／2月7日～2月14日（pg/m3）": "0.037",
            "(備考)6": "",
            "(8)練馬区石神井町局／2月7日～2月14日（pg/m3）": 0.058,
            "(備考)7": "",
            "(9)足立区西新井局／2月7日～2月14日（pg/m3）": "0.049",
            "(備考)8": "",
            "(10)葛飾区鎌倉／3月14日～3月21日（pg/m3）": "0.022",
            "(備考)9": "",
            "(11)江戸川区春江町局／2月7日～2月14日（pg/m3）": 0.043,
            "(備考)10": ""
        },
        {
            "row": 24,
            "column1": "実測濃度",
            "化合物の名称等": "ポリ塩化ジベンゾフラン",
            "column2": "1,2,3,7,8,9-HxCDF",
            "毒性等価係数": "0.1",
            "定量下限（pg/m3）": "0.008",
            "検出下限（pg/m3）": "0.002",
            "(1)中央区晴海局／2月7日～2月14日（pg/m3）": "0.004",
            "(備考)": "*",
            "(2)目黒区碑文谷局／2月7日～2月14日（pg/m3）": "N.D.",
            "(備考)1": "",
            "(3)大田区東糀谷局／2月7日～2月14日（pg/m3）": "0.003",
            "(備考)2": "*",
            "(4)世田谷区世田谷局／2月7日～2月14日（pg/m3）": "0.003",
            "(備考)3": "*",
            "(5)中野区若宮局／2月7日～2月14日（pg/m3）": "0.002",
            "(備考)4": "*",
            "(6)荒川区南千住局／2月7日～2月14日（pg/m3）": 0.004,
            "(備考)5": "*",
            "(7)板橋区本町局／2月7日～2月14日（pg/m3）": "0.003",
            "(備考)6": "*",
            "(8)練馬区石神井町局／2月7日～2月14日（pg/m3）": 0.005,
            "(備考)7": "*",
            "(9)足立区西新井局／2月7日～2月14日（pg/m3）": "0.003",
            "(備考)8": "*",
            "(10)葛飾区鎌倉／3月14日～3月21日（pg/m3）": "N.D.",
            "(備考)9": "",
            "(11)江戸川区春江町局／2月7日～2月14日（pg/m3）": 0.003,
            "(備考)10": "*"
        },
        {
            "row": 25,
            "column1": "実測濃度",
            "化合物の名称等": "ポリ塩化ジベンゾフラン",
            "column2": "2,3,4,6,7,8 + 1,2,3,6,8,9-HxCDF",
            "毒性等価係数": "0.1",
            "定量下限（pg/m3）": "0.010",
            "検出下限（pg/m3）": "0.003",
            "(1)中央区晴海局／2月7日～2月14日（pg/m3）": "0.039",
            "(備考)": "",
            "(2)目黒区碑文谷局／2月7日～2月14日（pg/m3）": "0.024",
            "(備考)1": "",
            "(3)大田区東糀谷局／2月7日～2月14日（pg/m3）": "0.024",
            "(備考)2": "",
            "(4)世田谷区世田谷局／2月7日～2月14日（pg/m3）": "0.036",
            "(備考)3": "",
            "(5)中野区若宮局／2月7日～2月14日（pg/m3）": "0.039",
            "(備考)4": "",
            "(6)荒川区南千住局／2月7日～2月14日（pg/m3）": 0.05,
            "(備考)5": "",
            "(7)板橋区本町局／2月7日～2月14日（pg/m3）": "0.045",
            "(備考)6": "",
            "(8)練馬区石神井町局／2月7日～2月14日（pg/m3）": 0.077,
            "(備考)7": "",
            "(9)足立区西新井局／2月7日～2月14日（pg/m3）": "0.063",
            "(備考)8": "",
            "(10)葛飾区鎌倉／3月14日～3月21日（pg/m3）": "0.027",
            "(備考)9": "",
            "(11)江戸川区春江町局／2月7日～2月14日（pg/m3）": 0.049,
            "(備考)10": ""
        },
        {
            "row": 26,
            "column1": "実測濃度",
            "化合物の名称等": "ポリ塩化ジベンゾフラン",
            "column2": "HxCDFs",
            "毒性等価係数": "－",
            "定量下限（pg/m3）": "0.008",
            "検出下限（pg/m3）": "0.002",
            "(1)中央区晴海局／2月7日～2月14日（pg/m3）": "0.33",
            "(備考)": "",
            "(2)目黒区碑文谷局／2月7日～2月14日（pg/m3）": "0.19",
            "(備考)1": "",
            "(3)大田区東糀谷局／2月7日～2月14日（pg/m3）": "0.2",
            "(備考)2": "",
            "(4)世田谷区世田谷局／2月7日～2月14日（pg/m3）": "0.29",
            "(備考)3": "",
            "(5)中野区若宮局／2月7日～2月14日（pg/m3）": "0.31",
            "(備考)4": "",
            "(6)荒川区南千住局／2月7日～2月14日（pg/m3）": 0.43,
            "(備考)5": "",
            "(7)板橋区本町局／2月7日～2月14日（pg/m3）": "0.36",
            "(備考)6": "",
            "(8)練馬区石神井町局／2月7日～2月14日（pg/m3）": 0.58,
            "(備考)7": "",
            "(9)足立区西新井局／2月7日～2月14日（pg/m3）": "0.52",
            "(備考)8": "",
            "(10)葛飾区鎌倉／3月14日～3月21日（pg/m3）": "0.22",
            "(備考)9": "",
            "(11)江戸川区春江町局／2月7日～2月14日（pg/m3）": 0.41,
            "(備考)10": ""
        },
        {
            "row": 27,
            "column1": "実測濃度",
            "化合物の名称等": "ポリ塩化ジベンゾフラン",
            "column2": "1,2,3,4,6,7,8-HpCDF",
            "毒性等価係数": "0.01",
            "定量下限（pg/m3）": "0.009",
            "検出下限（pg/m3）": "0.003",
            "(1)中央区晴海局／2月7日～2月14日（pg/m3）": "0.1",
            "(備考)": "",
            "(2)目黒区碑文谷局／2月7日～2月14日（pg/m3）": "0.063",
            "(備考)1": "",
            "(3)大田区東糀谷局／2月7日～2月14日（pg/m3）": "0.069",
            "(備考)2": "",
            "(4)世田谷区世田谷局／2月7日～2月14日（pg/m3）": "0.098",
            "(備考)3": "",
            "(5)中野区若宮局／2月7日～2月14日（pg/m3）": "0.12",
            "(備考)4": "",
            "(6)荒川区南千住局／2月7日～2月14日（pg/m3）": 0.13,
            "(備考)5": "",
            "(7)板橋区本町局／2月7日～2月14日（pg/m3）": "0.13",
            "(備考)6": "",
            "(8)練馬区石神井町局／2月7日～2月14日（pg/m3）": 0.24,
            "(備考)7": "",
            "(9)足立区西新井局／2月7日～2月14日（pg/m3）": "0.16",
            "(備考)8": "",
            "(10)葛飾区鎌倉／3月14日～3月21日（pg/m3）": "0.087",
            "(備考)9": "",
            "(11)江戸川区春江町局／2月7日～2月14日（pg/m3）": 0.12,
            "(備考)10": ""
        },
        {
            "row": 28,
            "column1": "実測濃度",
            "化合物の名称等": "ポリ塩化ジベンゾフラン",
            "column2": "1,2,3,4,7,8,9-HpCDF",
            "毒性等価係数": "0.01",
            "定量下限（pg/m3）": "0.010",
            "検出下限（pg/m3）": "0.003",
            "(1)中央区晴海局／2月7日～2月14日（pg/m3）": "0.018",
            "(備考)": "",
            "(2)目黒区碑文谷局／2月7日～2月14日（pg/m3）": "0.008",
            "(備考)1": "*",
            "(3)大田区東糀谷局／2月7日～2月14日（pg/m3）": "0.009",
            "(備考)2": "*",
            "(4)世田谷区世田谷局／2月7日～2月14日（pg/m3）": "0.013",
            "(備考)3": "",
            "(5)中野区若宮局／2月7日～2月14日（pg/m3）": "0.015",
            "(備考)4": "",
            "(6)荒川区南千住局／2月7日～2月14日（pg/m3）": 0.021,
            "(備考)5": "",
            "(7)板橋区本町局／2月7日～2月14日（pg/m3）": "0.018",
            "(備考)6": "",
            "(8)練馬区石神井町局／2月7日～2月14日（pg/m3）": 0.031,
            "(備考)7": "",
            "(9)足立区西新井局／2月7日～2月14日（pg/m3）": "0.023",
            "(備考)8": "",
            "(10)葛飾区鎌倉／3月14日～3月21日（pg/m3）": "0.012",
            "(備考)9": "",
            "(11)江戸川区春江町局／2月7日～2月14日（pg/m3）": 0.018,
            "(備考)10": ""
        },
        {
            "row": 29,
            "column1": "実測濃度",
            "化合物の名称等": "ポリ塩化ジベンゾフラン",
            "column2": "HpCDFs",
            "毒性等価係数": "－",
            "定量下限（pg/m3）": "0.009",
            "検出下限（pg/m3）": "0.003",
            "(1)中央区晴海局／2月7日～2月14日（pg/m3）": "0.17",
            "(備考)": "",
            "(2)目黒区碑文谷局／2月7日～2月14日（pg/m3）": "0.1",
            "(備考)1": "",
            "(3)大田区東糀谷局／2月7日～2月14日（pg/m3）": "0.11",
            "(備考)2": "",
            "(4)世田谷区世田谷局／2月7日～2月14日（pg/m3）": "0.16",
            "(備考)3": "",
            "(5)中野区若宮局／2月7日～2月14日（pg/m3）": "0.18",
            "(備考)4": "",
            "(6)荒川区南千住局／2月7日～2月14日（pg/m3）": 0.22,
            "(備考)5": "",
            "(7)板橋区本町局／2月7日～2月14日（pg/m3）": "0.2",
            "(備考)6": "",
            "(8)練馬区石神井町局／2月7日～2月14日（pg/m3）": 0.37,
            "(備考)7": "",
            "(9)足立区西新井局／2月7日～2月14日（pg/m3）": "0.26",
            "(備考)8": "",
            "(10)葛飾区鎌倉／3月14日～3月21日（pg/m3）": "0.14",
            "(備考)9": "",
            "(11)江戸川区春江町局／2月7日～2月14日（pg/m3）": 0.2,
            "(備考)10": ""
        },
        {
            "row": 30,
            "column1": "実測濃度",
            "化合物の名称等": "ポリ塩化ジベンゾフラン",
            "column2": "OCDF",
            "毒性等価係数": "0.0003",
            "定量下限（pg/m3）": "0.024",
            "検出下限（pg/m3）": "0.008",
            "(1)中央区晴海局／2月7日～2月14日（pg/m3）": "0.079",
            "(備考)": "",
            "(2)目黒区碑文谷局／2月7日～2月14日（pg/m3）": "0.038",
            "(備考)1": "",
            "(3)大田区東糀谷局／2月7日～2月14日（pg/m3）": "0.044",
            "(備考)2": "",
            "(4)世田谷区世田谷局／2月7日～2月14日（pg/m3）": "0.057",
            "(備考)3": "",
            "(5)中野区若宮局／2月7日～2月14日（pg/m3）": "0.067",
            "(備考)4": "",
            "(6)荒川区南千住局／2月7日～2月14日（pg/m3）": 0.1,
            "(備考)5": "",
            "(7)板橋区本町局／2月7日～2月14日（pg/m3）": "0.079",
            "(備考)6": "",
            "(8)練馬区石神井町局／2月7日～2月14日（pg/m3）": 0.17,
            "(備考)7": "",
            "(9)足立区西新井局／2月7日～2月14日（pg/m3）": "0.13",
            "(備考)8": "",
            "(10)葛飾区鎌倉／3月14日～3月21日（pg/m3）": "0.064",
            "(備考)9": "",
            "(11)江戸川区春江町局／2月7日～2月14日（pg/m3）": 0.078,
            "(備考)10": ""
        },
        {
            "row": 31,
            "column1": "実測濃度",
            "化合物の名称等": "ポリ塩化ジベンゾフラン",
            "column2": "Total　PCDFs",
            "毒性等価係数": "－",
            "定量下限（pg/m3）": "－",
            "検出下限（pg/m3）": "－",
            "(1)中央区晴海局／2月7日～2月14日（pg/m3）": "1.5",
            "(備考)": "",
            "(2)目黒区碑文谷局／2月7日～2月14日（pg/m3）": "0.93",
            "(備考)1": "",
            "(3)大田区東糀谷局／2月7日～2月14日（pg/m3）": "1.1",
            "(備考)2": "",
            "(4)世田谷区世田谷局／2月7日～2月14日（pg/m3）": "1.3",
            "(備考)3": "",
            "(5)中野区若宮局／2月7日～2月14日（pg/m3）": "1.3",
            "(備考)4": "",
            "(6)荒川区南千住局／2月7日～2月14日（pg/m3）": 2.3,
            "(備考)5": "",
            "(7)板橋区本町局／2月7日～2月14日（pg/m3）": "1.7",
            "(備考)6": "",
            "(8)練馬区石神井町局／2月7日～2月14日（pg/m3）": 3.1,
            "(備考)7": "",
            "(9)足立区西新井局／2月7日～2月14日（pg/m3）": "2.5",
            "(備考)8": "",
            "(10)葛飾区鎌倉／3月14日～3月21日（pg/m3）": "1.4",
            "(備考)9": "",
            "(11)江戸川区春江町局／2月7日～2月14日（pg/m3）": 2.1,
            "(備考)10": ""
        },
        {
            "row": 32,
            "column1": "実測濃度",
            "化合物の名称等": "Total　（PCDFs＋PCDDs）",
            "column2": "",
            "毒性等価係数": "－",
            "定量下限（pg/m3）": "－",
            "検出下限（pg/m3）": "－",
            "(1)中央区晴海局／2月7日～2月14日（pg/m3）": "2.5",
            "(備考)": "",
            "(2)目黒区碑文谷局／2月7日～2月14日（pg/m3）": "1.5",
            "(備考)1": "",
            "(3)大田区東糀谷局／2月7日～2月14日（pg/m3）": "1.7",
            "(備考)2": "",
            "(4)世田谷区世田谷局／2月7日～2月14日（pg/m3）": "2.1",
            "(備考)3": "",
            "(5)中野区若宮局／2月7日～2月14日（pg/m3）": "2.1",
            "(備考)4": "",
            "(6)荒川区南千住局／2月7日～2月14日（pg/m3）": 3.7,
            "(備考)5": "",
            "(7)板橋区本町局／2月7日～2月14日（pg/m3）": "2.8",
            "(備考)6": "",
            "(8)練馬区石神井町局／2月7日～2月14日（pg/m3）": 5.1,
            "(備考)7": "",
            "(9)足立区西新井局／2月7日～2月14日（pg/m3）": "4",
            "(備考)8": "",
            "(10)葛飾区鎌倉／3月14日～3月21日（pg/m3）": "2.2",
            "(備考)9": "",
            "(11)江戸川区春江町局／2月7日～2月14日（pg/m3）": 3.3,
            "(備考)10": ""
        },
        {
            "row": 33,
            "column1": "実測濃度",
            "化合物の名称等": "コプラナ|ポリ塩化ビフェニル",
            "column2": "3,4,4',5-TeCB(#81)",
            "毒性等価係数": "0.0003",
            "定量下限（pg/m3）": "0.006",
            "検出下限（pg/m3）": "0.002",
            "(1)中央区晴海局／2月7日～2月14日（pg/m3）": "0.016",
            "(備考)": "",
            "(2)目黒区碑文谷局／2月7日～2月14日（pg/m3）": "0.009",
            "(備考)1": "",
            "(3)大田区東糀谷局／2月7日～2月14日（pg/m3）": "0.011",
            "(備考)2": "",
            "(4)世田谷区世田谷局／2月7日～2月14日（pg/m3）": "0.013",
            "(備考)3": "",
            "(5)中野区若宮局／2月7日～2月14日（pg/m3）": "0.011",
            "(備考)4": "",
            "(6)荒川区南千住局／2月7日～2月14日（pg/m3）": 0.022,
            "(備考)5": "",
            "(7)板橋区本町局／2月7日～2月14日（pg/m3）": "0.017",
            "(備考)6": "",
            "(8)練馬区石神井町局／2月7日～2月14日（pg/m3）": 0.028,
            "(備考)7": "",
            "(9)足立区西新井局／2月7日～2月14日（pg/m3）": "0.024",
            "(備考)8": "",
            "(10)葛飾区鎌倉／3月14日～3月21日（pg/m3）": "0.018",
            "(備考)9": "",
            "(11)江戸川区春江町局／2月7日～2月14日（pg/m3）": 0.021,
            "(備考)10": ""
        },
        {
            "row": 34,
            "column1": "実測濃度",
            "化合物の名称等": "コプラナ|ポリ塩化ビフェニル",
            "column2": "3,3',4,4'-TeCB(#77)",
            "毒性等価係数": "0.0001",
            "定量下限（pg/m3）": "0.005",
            "検出下限（pg/m3）": "0.002",
            "(1)中央区晴海局／2月7日～2月14日（pg/m3）": "0.14",
            "(備考)": "",
            "(2)目黒区碑文谷局／2月7日～2月14日（pg/m3）": "0.074",
            "(備考)1": "",
            "(3)大田区東糀谷局／2月7日～2月14日（pg/m3）": "0.11",
            "(備考)2": "",
            "(4)世田谷区世田谷局／2月7日～2月14日（pg/m3）": "0.11",
            "(備考)3": "",
            "(5)中野区若宮局／2月7日～2月14日（pg/m3）": "0.084",
            "(備考)4": "",
            "(6)荒川区南千住局／2月7日～2月14日（pg/m3）": 0.12,
            "(備考)5": "",
            "(7)板橋区本町局／2月7日～2月14日（pg/m3）": "0.09",
            "(備考)6": "",
            "(8)練馬区石神井町局／2月7日～2月14日（pg/m3）": 0.14,
            "(備考)7": "",
            "(9)足立区西新井局／2月7日～2月14日（pg/m3）": "0.1",
            "(備考)8": "",
            "(10)葛飾区鎌倉／3月14日～3月21日（pg/m3）": "0.17",
            "(備考)9": "",
            "(11)江戸川区春江町局／2月7日～2月14日（pg/m3）": 0.12,
            "(備考)10": ""
        },
        {
            "row": 35,
            "column1": "実測濃度",
            "化合物の名称等": "コプラナ|ポリ塩化ビフェニル",
            "column2": "3,3',4,4',5-PeCB(#126)",
            "毒性等価係数": "0.1",
            "定量下限（pg/m3）": "0.006",
            "検出下限（pg/m3）": "0.002",
            "(1)中央区晴海局／2月7日～2月14日（pg/m3）": "0.024",
            "(備考)": "",
            "(2)目黒区碑文谷局／2月7日～2月14日（pg/m3）": "0.014",
            "(備考)1": "",
            "(3)大田区東糀谷局／2月7日～2月14日（pg/m3）": "0.015",
            "(備考)2": "",
            "(4)世田谷区世田谷局／2月7日～2月14日（pg/m3）": "0.016",
            "(備考)3": "",
            "(5)中野区若宮局／2月7日～2月14日（pg/m3）": "0.016",
            "(備考)4": "",
            "(6)荒川区南千住局／2月7日～2月14日（pg/m3）": 0.035,
            "(備考)5": "",
            "(7)板橋区本町局／2月7日～2月14日（pg/m3）": "0.023",
            "(備考)6": "",
            "(8)練馬区石神井町局／2月7日～2月14日（pg/m3）": 0.039,
            "(備考)7": "",
            "(9)足立区西新井局／2月7日～2月14日（pg/m3）": "0.037",
            "(備考)8": "",
            "(10)葛飾区鎌倉／3月14日～3月21日（pg/m3）": "0.023",
            "(備考)9": "",
            "(11)江戸川区春江町局／2月7日～2月14日（pg/m3）": 0.029,
            "(備考)10": ""
        },
        {
            "row": 36,
            "column1": "実測濃度",
            "化合物の名称等": "コプラナ|ポリ塩化ビフェニル",
            "column2": "3,3',4,4',5,5'-HxCB(#169)",
            "毒性等価係数": "0.03",
            "定量下限（pg/m3）": "0.006",
            "検出下限（pg/m3）": "0.002",
            "(1)中央区晴海局／2月7日～2月14日（pg/m3）": "0.006",
            "(備考)": "",
            "(2)目黒区碑文谷局／2月7日～2月14日（pg/m3）": "0.004",
            "(備考)1": "*",
            "(3)大田区東糀谷局／2月7日～2月14日（pg/m3）": "0.004",
            "(備考)2": "*",
            "(4)世田谷区世田谷局／2月7日～2月14日（pg/m3）": "0.006",
            "(備考)3": "",
            "(5)中野区若宮局／2月7日～2月14日（pg/m3）": "0.006",
            "(備考)4": "",
            "(6)荒川区南千住局／2月7日～2月14日（pg/m3）": 0.011,
            "(備考)5": "",
            "(7)板橋区本町局／2月7日～2月14日（pg/m3）": "0.007",
            "(備考)6": "",
            "(8)練馬区石神井町局／2月7日～2月14日（pg/m3）": 0.012,
            "(備考)7": "",
            "(9)足立区西新井局／2月7日～2月14日（pg/m3）": "0.013",
            "(備考)8": "",
            "(10)葛飾区鎌倉／3月14日～3月21日（pg/m3）": "0.004",
            "(備考)9": "*",
            "(11)江戸川区春江町局／2月7日～2月14日（pg/m3）": 0.008,
            "(備考)10": ""
        },
        {
            "row": 37,
            "column1": "実測濃度",
            "化合物の名称等": "コプラナ|ポリ塩化ビフェニル",
            "column2": "Total　ﾉﾝｵﾙﾄ体",
            "毒性等価係数": "－",
            "定量下限（pg/m3）": "－",
            "検出下限（pg/m3）": "－",
            "(1)中央区晴海局／2月7日～2月14日（pg/m3）": "0.19",
            "(備考)": "",
            "(2)目黒区碑文谷局／2月7日～2月14日（pg/m3）": "0.1",
            "(備考)1": "",
            "(3)大田区東糀谷局／2月7日～2月14日（pg/m3）": "0.14",
            "(備考)2": "",
            "(4)世田谷区世田谷局／2月7日～2月14日（pg/m3）": "0.15",
            "(備考)3": "",
            "(5)中野区若宮局／2月7日～2月14日（pg/m3）": "0.12",
            "(備考)4": "",
            "(6)荒川区南千住局／2月7日～2月14日（pg/m3）": 0.19,
            "(備考)5": "",
            "(7)板橋区本町局／2月7日～2月14日（pg/m3）": "0.14",
            "(備考)6": "",
            "(8)練馬区石神井町局／2月7日～2月14日（pg/m3）": 0.22,
            "(備考)7": "",
            "(9)足立区西新井局／2月7日～2月14日（pg/m3）": "0.17",
            "(備考)8": "",
            "(10)葛飾区鎌倉／3月14日～3月21日（pg/m3）": "0.22",
            "(備考)9": "",
            "(11)江戸川区春江町局／2月7日～2月14日（pg/m3）": 0.18,
            "(備考)10": ""
        },
        {
            "row": 38,
            "column1": "実測濃度",
            "化合物の名称等": "コプラナ|ポリ塩化ビフェニル",
            "column2": "2',3,4,4',5-PeCB(#123)",
            "毒性等価係数": "0.00003",
            "定量下限（pg/m3）": "0.005",
            "検出下限（pg/m3）": "0.002",
            "(1)中央区晴海局／2月7日～2月14日（pg/m3）": "0.029",
            "(備考)": "",
            "(2)目黒区碑文谷局／2月7日～2月14日（pg/m3）": "0.012",
            "(備考)1": "",
            "(3)大田区東糀谷局／2月7日～2月14日（pg/m3）": "0.017",
            "(備考)2": "",
            "(4)世田谷区世田谷局／2月7日～2月14日（pg/m3）": "0.018",
            "(備考)3": "",
            "(5)中野区若宮局／2月7日～2月14日（pg/m3）": "0.009",
            "(備考)4": "",
            "(6)荒川区南千住局／2月7日～2月14日（pg/m3）": 0.016,
            "(備考)5": "",
            "(7)板橋区本町局／2月7日～2月14日（pg/m3）": "0.015",
            "(備考)6": "",
            "(8)練馬区石神井町局／2月7日～2月14日（pg/m3）": 0.023,
            "(備考)7": "",
            "(9)足立区西新井局／2月7日～2月14日（pg/m3）": "0.014",
            "(備考)8": "",
            "(10)葛飾区鎌倉／3月14日～3月21日（pg/m3）": "0.024",
            "(備考)9": "",
            "(11)江戸川区春江町局／2月7日～2月14日（pg/m3）": 0.017,
            "(備考)10": ""
        },
        {
            "row": 39,
            "column1": "実測濃度",
            "化合物の名称等": "コプラナ|ポリ塩化ビフェニル",
            "column2": "2,3',4,4',5-PeCB(#118)",
            "毒性等価係数": "0.00003",
            "定量下限（pg/m3）": "0.010",
            "検出下限（pg/m3）": "0.003",
            "(1)中央区晴海局／2月7日～2月14日（pg/m3）": "1.2",
            "(備考)": "",
            "(2)目黒区碑文谷局／2月7日～2月14日（pg/m3）": "0.37",
            "(備考)1": "",
            "(3)大田区東糀谷局／2月7日～2月14日（pg/m3）": "0.57",
            "(備考)2": "",
            "(4)世田谷区世田谷局／2月7日～2月14日（pg/m3）": "0.72",
            "(備考)3": "",
            "(5)中野区若宮局／2月7日～2月14日（pg/m3）": "0.27",
            "(備考)4": "",
            "(6)荒川区南千住局／2月7日～2月14日（pg/m3）": 0.46,
            "(備考)5": "",
            "(7)板橋区本町局／2月7日～2月14日（pg/m3）": "0.41",
            "(備考)6": "",
            "(8)練馬区石神井町局／2月7日～2月14日（pg/m3）": 0.63,
            "(備考)7": "",
            "(9)足立区西新井局／2月7日～2月14日（pg/m3）": "0.34",
            "(備考)8": "",
            "(10)葛飾区鎌倉／3月14日～3月21日（pg/m3）": "0.83",
            "(備考)9": "",
            "(11)江戸川区春江町局／2月7日～2月14日（pg/m3）": 0.54,
            "(備考)10": ""
        },
        {
            "row": 40,
            "column1": "実測濃度",
            "化合物の名称等": "コプラナ|ポリ塩化ビフェニル",
            "column2": "2,3,3',4,4'-PeCB(#105)",
            "毒性等価係数": "0.00003",
            "定量下限（pg/m3）": "0.010",
            "検出下限（pg/m3）": "0.003",
            "(1)中央区晴海局／2月7日～2月14日（pg/m3）": "0.44",
            "(備考)": "",
            "(2)目黒区碑文谷局／2月7日～2月14日（pg/m3）": "0.15",
            "(備考)1": "",
            "(3)大田区東糀谷局／2月7日～2月14日（pg/m3）": "0.23",
            "(備考)2": "",
            "(4)世田谷区世田谷局／2月7日～2月14日（pg/m3）": "0.25",
            "(備考)3": "",
            "(5)中野区若宮局／2月7日～2月14日（pg/m3）": "0.12",
            "(備考)4": "",
            "(6)荒川区南千住局／2月7日～2月14日（pg/m3）": 0.19,
            "(備考)5": "",
            "(7)板橋区本町局／2月7日～2月14日（pg/m3）": "0.17",
            "(備考)6": "",
            "(8)練馬区石神井町局／2月7日～2月14日（pg/m3）": 0.26,
            "(備考)7": "",
            "(9)足立区西新井局／2月7日～2月14日（pg/m3）": "0.15",
            "(備考)8": "",
            "(10)葛飾区鎌倉／3月14日～3月21日（pg/m3）": "0.32",
            "(備考)9": "",
            "(11)江戸川区春江町局／2月7日～2月14日（pg/m3）": 0.21,
            "(備考)10": ""
        },
        {
            "row": 41,
            "column1": "実測濃度",
            "化合物の名称等": "コプラナ|ポリ塩化ビフェニル",
            "column2": "2,3,4,4',5-PeCB(#114)",
            "毒性等価係数": "0.00003",
            "定量下限（pg/m3）": "0.006",
            "検出下限（pg/m3）": "0.002",
            "(1)中央区晴海局／2月7日～2月14日（pg/m3）": "0.039",
            "(備考)": "",
            "(2)目黒区碑文谷局／2月7日～2月14日（pg/m3）": "0.015",
            "(備考)1": "",
            "(3)大田区東糀谷局／2月7日～2月14日（pg/m3）": "0.021",
            "(備考)2": "",
            "(4)世田谷区世田谷局／2月7日～2月14日（pg/m3）": "0.026",
            "(備考)3": "",
            "(5)中野区若宮局／2月7日～2月14日（pg/m3）": "0.011",
            "(備考)4": "",
            "(6)荒川区南千住局／2月7日～2月14日（pg/m3）": 0.023,
            "(備考)5": "",
            "(7)板橋区本町局／2月7日～2月14日（pg/m3）": "0.019",
            "(備考)6": "",
            "(8)練馬区石神井町局／2月7日～2月14日（pg/m3）": 0.03,
            "(備考)7": "",
            "(9)足立区西新井局／2月7日～2月14日（pg/m3）": "0.021",
            "(備考)8": "",
            "(10)葛飾区鎌倉／3月14日～3月21日（pg/m3）": "0.032",
            "(備考)9": "",
            "(11)江戸川区春江町局／2月7日～2月14日（pg/m3）": 0.022,
            "(備考)10": ""
        },
        {
            "row": 42,
            "column1": "実測濃度",
            "化合物の名称等": "コプラナ|ポリ塩化ビフェニル",
            "column2": "2,3',4,4',5,5'-HxCB(#167)",
            "毒性等価係数": "0.00003",
            "定量下限（pg/m3）": "0.006",
            "検出下限（pg/m3）": "0.002",
            "(1)中央区晴海局／2月7日～2月14日（pg/m3）": "0.042",
            "(備考)": "",
            "(2)目黒区碑文谷局／2月7日～2月14日（pg/m3）": "0.015",
            "(備考)1": "",
            "(3)大田区東糀谷局／2月7日～2月14日（pg/m3）": "0.02",
            "(備考)2": "",
            "(4)世田谷区世田谷局／2月7日～2月14日（pg/m3）": "0.015",
            "(備考)3": "",
            "(5)中野区若宮局／2月7日～2月14日（pg/m3）": "0.014",
            "(備考)4": "",
            "(6)荒川区南千住局／2月7日～2月14日（pg/m3）": 0.024,
            "(備考)5": "",
            "(7)板橋区本町局／2月7日～2月14日（pg/m3）": "0.019",
            "(備考)6": "",
            "(8)練馬区石神井町局／2月7日～2月14日（pg/m3）": 0.033,
            "(備考)7": "",
            "(9)足立区西新井局／2月7日～2月14日（pg/m3）": "0.022",
            "(備考)8": "",
            "(10)葛飾区鎌倉／3月14日～3月21日（pg/m3）": "0.027",
            "(備考)9": "",
            "(11)江戸川区春江町局／2月7日～2月14日（pg/m3）": 0.027,
            "(備考)10": ""
        },
        {
            "row": 43,
            "column1": "実測濃度",
            "化合物の名称等": "コプラナ|ポリ塩化ビフェニル",
            "column2": "2,3,3',4,4',5-HxCB(#156)",
            "毒性等価係数": "0.00003",
            "定量下限（pg/m3）": "0.006",
            "検出下限（pg/m3）": "0.002",
            "(1)中央区晴海局／2月7日～2月14日（pg/m3）": "0.087",
            "(備考)": "",
            "(2)目黒区碑文谷局／2月7日～2月14日（pg/m3）": "0.029",
            "(備考)1": "",
            "(3)大田区東糀谷局／2月7日～2月14日（pg/m3）": "0.039",
            "(備考)2": "",
            "(4)世田谷区世田谷局／2月7日～2月14日（pg/m3）": "0.034",
            "(備考)3": "",
            "(5)中野区若宮局／2月7日～2月14日（pg/m3）": "0.027",
            "(備考)4": "",
            "(6)荒川区南千住局／2月7日～2月14日（pg/m3）": 0.045,
            "(備考)5": "",
            "(7)板橋区本町局／2月7日～2月14日（pg/m3）": "0.037",
            "(備考)6": "",
            "(8)練馬区石神井町局／2月7日～2月14日（pg/m3）": 0.064,
            "(備考)7": "",
            "(9)足立区西新井局／2月7日～2月14日（pg/m3）": "0.045",
            "(備考)8": "",
            "(10)葛飾区鎌倉／3月14日～3月21日（pg/m3）": "0.057",
            "(備考)9": "",
            "(11)江戸川区春江町局／2月7日～2月14日（pg/m3）": 0.062,
            "(備考)10": ""
        },
        {
            "row": 44,
            "column1": "実測濃度",
            "化合物の名称等": "コプラナ|ポリ塩化ビフェニル",
            "column2": "2,3,3',4,4',5'-HxCB(#157)",
            "毒性等価係数": "0.00003",
            "定量下限（pg/m3）": "0.005",
            "検出下限（pg/m3）": "0.002",
            "(1)中央区晴海局／2月7日～2月14日（pg/m3）": "0.024",
            "(備考)": "",
            "(2)目黒区碑文谷局／2月7日～2月14日（pg/m3）": "0.009",
            "(備考)1": "",
            "(3)大田区東糀谷局／2月7日～2月14日（pg/m3）": "0.012",
            "(備考)2": "",
            "(4)世田谷区世田谷局／2月7日～2月14日（pg/m3）": "0.01",
            "(備考)3": "",
            "(5)中野区若宮局／2月7日～2月14日（pg/m3）": "0.009",
            "(備考)4": "",
            "(6)荒川区南千住局／2月7日～2月14日（pg/m3）": 0.017,
            "(備考)5": "",
            "(7)板橋区本町局／2月7日～2月14日（pg/m3）": "0.012",
            "(備考)6": "",
            "(8)練馬区石神井町局／2月7日～2月14日（pg/m3）": 0.021,
            "(備考)7": "",
            "(9)足立区西新井局／2月7日～2月14日（pg/m3）": "0.018",
            "(備考)8": "",
            "(10)葛飾区鎌倉／3月14日～3月21日（pg/m3）": "0.017",
            "(備考)9": "",
            "(11)江戸川区春江町局／2月7日～2月14日（pg/m3）": 0.019,
            "(備考)10": ""
        },
        {
            "row": 45,
            "column1": "実測濃度",
            "化合物の名称等": "コプラナ|ポリ塩化ビフェニル",
            "column2": "2,3,3',4,4',5,5'-HpCB(#189)",
            "毒性等価係数": "0.00003",
            "定量下限（pg/m3）": "0.006",
            "検出下限（pg/m3）": "0.002",
            "(1)中央区晴海局／2月7日～2月14日（pg/m3）": "0.013",
            "(備考)": "",
            "(2)目黒区碑文谷局／2月7日～2月14日（pg/m3）": "0.007",
            "(備考)1": "",
            "(3)大田区東糀谷局／2月7日～2月14日（pg/m3）": "0.008",
            "(備考)2": "",
            "(4)世田谷区世田谷局／2月7日～2月14日（pg/m3）": "0.009",
            "(備考)3": "",
            "(5)中野区若宮局／2月7日～2月14日（pg/m3）": "0.01",
            "(備考)4": "",
            "(6)荒川区南千住局／2月7日～2月14日（pg/m3）": 0.016,
            "(備考)5": "",
            "(7)板橋区本町局／2月7日～2月14日（pg/m3）": "0.011",
            "(備考)6": "",
            "(8)練馬区石神井町局／2月7日～2月14日（pg/m3）": 0.018,
            "(備考)7": "",
            "(9)足立区西新井局／2月7日～2月14日（pg/m3）": "0.02",
            "(備考)8": "",
            "(10)葛飾区鎌倉／3月14日～3月21日（pg/m3）": "0.008",
            "(備考)9": "",
            "(11)江戸川区春江町局／2月7日～2月14日（pg/m3）": 0.013,
            "(備考)10": ""
        },
        {
            "row": 46,
            "column1": "実測濃度",
            "化合物の名称等": "コプラナ|ポリ塩化ビフェニル",
            "column2": "Total　ﾓﾉｵﾙﾄ体",
            "毒性等価係数": "－",
            "定量下限（pg/m3）": "－",
            "検出下限（pg/m3）": "－",
            "(1)中央区晴海局／2月7日～2月14日（pg/m3）": "1.9",
            "(備考)": "",
            "(2)目黒区碑文谷局／2月7日～2月14日（pg/m3）": "0.61",
            "(備考)1": "",
            "(3)大田区東糀谷局／2月7日～2月14日（pg/m3）": "0.92",
            "(備考)2": "",
            "(4)世田谷区世田谷局／2月7日～2月14日（pg/m3）": "1.1",
            "(備考)3": "",
            "(5)中野区若宮局／2月7日～2月14日（pg/m3）": "0.47",
            "(備考)4": "",
            "(6)荒川区南千住局／2月7日～2月14日（pg/m3）": 0.79,
            "(備考)5": "",
            "(7)板橋区本町局／2月7日～2月14日（pg/m3）": "0.69",
            "(備考)6": "",
            "(8)練馬区石神井町局／2月7日～2月14日（pg/m3）": 1.1,
            "(備考)7": "",
            "(9)足立区西新井局／2月7日～2月14日（pg/m3）": "0.63",
            "(備考)8": "",
            "(10)葛飾区鎌倉／3月14日～3月21日（pg/m3）": "1.3",
            "(備考)9": "",
            "(11)江戸川区春江町局／2月7日～2月14日（pg/m3）": 0.91,
            "(備考)10": ""
        },
        {
            "row": 47,
            "column1": "実測濃度",
            "化合物の名称等": "コプラナ|ポリ塩化ビフェニル",
            "column2": "Total （ﾉﾝｵﾙﾄ体＋ﾓﾉｵﾙﾄ体）",
            "毒性等価係数": "－",
            "定量下限（pg/m3）": "－",
            "検出下限（pg/m3）": "－",
            "(1)中央区晴海局／2月7日～2月14日（pg/m3）": "2.1",
            "(備考)": "",
            "(2)目黒区碑文谷局／2月7日～2月14日（pg/m3）": "0.71",
            "(備考)1": "",
            "(3)大田区東糀谷局／2月7日～2月14日（pg/m3）": "1.1",
            "(備考)2": "",
            "(4)世田谷区世田谷局／2月7日～2月14日（pg/m3）": "1.2",
            "(備考)3": "",
            "(5)中野区若宮局／2月7日～2月14日（pg/m3）": "0.59",
            "(備考)4": "",
            "(6)荒川区南千住局／2月7日～2月14日（pg/m3）": 0.98,
            "(備考)5": "",
            "(7)板橋区本町局／2月7日～2月14日（pg/m3）": "0.83",
            "(備考)6": "",
            "(8)練馬区石神井町局／2月7日～2月14日（pg/m3）": 1.3,
            "(備考)7": "",
            "(9)足立区西新井局／2月7日～2月14日（pg/m3）": "0.8",
            "(備考)8": "",
            "(10)葛飾区鎌倉／3月14日～3月21日（pg/m3）": "1.5",
            "(備考)9": "",
            "(11)江戸川区春江町局／2月7日～2月14日（pg/m3）": 1.1,
            "(備考)10": ""
        },
        {
            "row": 48,
            "column1": "実測濃度",
            "化合物の名称等": "Total（PCDFs+PCDDs+ｺﾌﾟﾗﾅｰPCB）",
            "column2": "",
            "毒性等価係数": "－",
            "定量下限（pg/m3）": "－",
            "検出下限（pg/m3）": "－",
            "(1)中央区晴海局／2月7日～2月14日（pg/m3）": "4.5",
            "(備考)": "",
            "(2)目黒区碑文谷局／2月7日～2月14日（pg/m3）": "2.3",
            "(備考)1": "",
            "(3)大田区東糀谷局／2月7日～2月14日（pg/m3）": "2.8",
            "(備考)2": "",
            "(4)世田谷区世田谷局／2月7日～2月14日（pg/m3）": "3.3",
            "(備考)3": "",
            "(5)中野区若宮局／2月7日～2月14日（pg/m3）": "2.7",
            "(備考)4": "",
            "(6)荒川区南千住局／2月7日～2月14日（pg/m3）": 4.7,
            "(備考)5": "",
            "(7)板橋区本町局／2月7日～2月14日（pg/m3）": "3.6",
            "(備考)6": "",
            "(8)練馬区石神井町局／2月7日～2月14日（pg/m3）": 6.4,
            "(備考)7": "",
            "(9)足立区西新井局／2月7日～2月14日（pg/m3）": "4.8",
            "(備考)8": "",
            "(10)葛飾区鎌倉／3月14日～3月21日（pg/m3）": "3.7",
            "(備考)9": "",
            "(11)江戸川区春江町局／2月7日～2月14日（pg/m3）": 4.4,
            "(備考)10": ""
        },
        {
            "row": 49,
            "column1": "毒性等量",
            "化合物の名称等": "PCDDs",
            "column2": "",
            "毒性等価係数": "－",
            "定量下限（pg/m3）": "－",
            "検出下限（pg/m3）": "－",
            "(1)中央区晴海局／2月7日～2月14日（pg/m3）": "0.011",
            "(備考)": "",
            "(2)目黒区碑文谷局／2月7日～2月14日（pg/m3）": "0.0073",
            "(備考)1": "",
            "(3)大田区東糀谷局／2月7日～2月14日（pg/m3）": "0.0084",
            "(備考)2": "",
            "(4)世田谷区世田谷局／2月7日～2月14日（pg/m3）": "0.01",
            "(備考)3": "",
            "(5)中野区若宮局／2月7日～2月14日（pg/m3）": "0.01",
            "(備考)4": "",
            "(6)荒川区南千住局／2月7日～2月14日（pg/m3）": 0.018,
            "(備考)5": "",
            "(7)板橋区本町局／2月7日～2月14日（pg/m3）": "0.012",
            "(備考)6": "",
            "(8)練馬区石神井町局／2月7日～2月14日（pg/m3）": 0.021,
            "(備考)7": "",
            "(9)足立区西新井局／2月7日～2月14日（pg/m3）": "0.015",
            "(備考)8": "",
            "(10)葛飾区鎌倉／3月14日～3月21日（pg/m3）": "0.0076",
            "(備考)9": "",
            "(11)江戸川区春江町局／2月7日～2月14日（pg/m3）": 0.02,
            "(備考)10": ""
        },
        {
            "row": 50,
            "column1": "毒性等量",
            "化合物の名称等": "PCDFs",
            "column2": "",
            "毒性等価係数": "－",
            "定量下限（pg/m3）": "－",
            "検出下限（pg/m3）": "－",
            "(1)中央区晴海局／2月7日～2月14日（pg/m3）": "0.023",
            "(備考)": "",
            "(2)目黒区碑文谷局／2月7日～2月14日（pg/m3）": "0.013",
            "(備考)1": "",
            "(3)大田区東糀谷局／2月7日～2月14日（pg/m3）": "0.014",
            "(備考)2": "",
            "(4)世田谷区世田谷局／2月7日～2月14日（pg/m3）": "0.019",
            "(備考)3": "",
            "(5)中野区若宮局／2月7日～2月14日（pg/m3）": "0.021",
            "(備考)4": "",
            "(6)荒川区南千住局／2月7日～2月14日（pg/m3）": 0.029,
            "(備考)5": "",
            "(7)板橋区本町局／2月7日～2月14日（pg/m3）": "0.025",
            "(備考)6": "",
            "(8)練馬区石神井町局／2月7日～2月14日（pg/m3）": 0.04,
            "(備考)7": "",
            "(9)足立区西新井局／2月7日～2月14日（pg/m3）": "0.033",
            "(備考)8": "",
            "(10)葛飾区鎌倉／3月14日～3月21日（pg/m3）": "0.015",
            "(備考)9": "",
            "(11)江戸川区春江町局／2月7日～2月14日（pg/m3）": 0.029,
            "(備考)10": ""
        },
        {
            "row": 51,
            "column1": "毒性等量",
            "化合物の名称等": "co-PCBs",
            "column2": "",
            "毒性等価係数": "－",
            "定量下限（pg/m3）": "－",
            "検出下限（pg/m3）": "－",
            "(1)中央区晴海局／2月7日～2月14日（pg/m3）": "0.0027",
            "(備考)": "",
            "(2)目黒区碑文谷局／2月7日～2月14日（pg/m3）": "0.0015",
            "(備考)1": "",
            "(3)大田区東糀谷局／2月7日～2月14日（pg/m3）": "0.0017",
            "(備考)2": "",
            "(4)世田谷区世田谷局／2月7日～2月14日（pg/m3）": "0.0018",
            "(備考)3": "",
            "(5)中野区若宮局／2月7日～2月14日（pg/m3）": "0.0018",
            "(備考)4": "",
            "(6)荒川区南千住局／2月7日～2月14日（pg/m3）": 0.0039,
            "(備考)5": "",
            "(7)板橋区本町局／2月7日～2月14日（pg/m3）": "0.0025",
            "(備考)6": "",
            "(8)練馬区石神井町局／2月7日～2月14日（pg/m3）": 0.0043,
            "(備考)7": "",
            "(9)足立区西新井局／2月7日～2月14日（pg/m3）": "0.0041",
            "(備考)8": "",
            "(10)葛飾区鎌倉／3月14日～3月21日（pg/m3）": "0.0025",
            "(備考)9": "",
            "(11)江戸川区春江町局／2月7日～2月14日（pg/m3）": 0.0032,
            "(備考)10": ""
        },
        {
            "row": 52,
            "column1": "毒性等量",
            "化合物の名称等": "Ｔotal DXN",
            "column2": "",
            "毒性等価係数": "－",
            "定量下限（pg/m3）": "－",
            "検出下限（pg/m3）": "－",
            "(1)中央区晴海局／2月7日～2月14日（pg/m3）": "0.037",
            "(備考)": "",
            "(2)目黒区碑文谷局／2月7日～2月14日（pg/m3）": "0.022",
            "(備考)1": "",
            "(3)大田区東糀谷局／2月7日～2月14日（pg/m3）": "0.024",
            "(備考)2": "",
            "(4)世田谷区世田谷局／2月7日～2月14日（pg/m3）": "0.031",
            "(備考)3": "",
            "(5)中野区若宮局／2月7日～2月14日（pg/m3）": "0.033",
            "(備考)4": "",
            "(6)荒川区南千住局／2月7日～2月14日（pg/m3）": 0.051,
            "(備考)5": "",
            "(7)板橋区本町局／2月7日～2月14日（pg/m3）": "0.039",
            "(備考)6": "",
            "(8)練馬区石神井町局／2月7日～2月14日（pg/m3）": 0.066,
            "(備考)7": "",
            "(9)足立区西新井局／2月7日～2月14日（pg/m3）": "0.052",
            "(備考)8": "",
            "(10)葛飾区鎌倉／3月14日～3月21日（pg/m3）": "0.025",
            "(備考)9": "",
            "(11)江戸川区春江町局／2月7日～2月14日（pg/m3）": 0.052,
            "(備考)10": ""
        }
    ]
}